libts/__init__.py
libts/libts.dll
libts/libts.py
libts/libts.so
libts-0.0.2.dist-info/licenses/LICENSE
libts-0.0.2.dist-info/METADATA
libts-0.0.2.dist-info/WHEEL
libts-0.0.2.dist-info/top_level.txt
libts-0.0.2.dist-info/RECORD
