Metadata-Version: 2.4
Name: libts
Version: 0.0.2
Summary: 一个用于验证 RFC3161 时间戳签名的库
Home-page: https://github.com/Brassinolide/libts-py
Author: Brassinolide
Author-email: contact@crackme.net
Classifier: Programming Language :: Python :: 3
Classifier: Operating System :: Microsoft :: Windows
Classifier: Operating System :: POSIX :: Linux
License-File: LICENSE
Dynamic: author
Dynamic: author-email
Dynamic: classifier
Dynamic: description
Dynamic: description-content-type
Dynamic: home-page
Dynamic: license-file
Dynamic: summary
